hydrator/__init__.py
hydrator/__main__.py
hydrator/_hydrator.py
hydrator/file_systems/__init__.py
hydrator/file_systems/nextcloud.py
hydrator/hydrators/__init__.py
hydrator/hydrators/bash_profile.py
hydrator/hydrators/commands.py
hydrator/hydrators/gitconfig.py
hydrator/hydrators/test_commands.py
hydrator/lib/__init__.py
hydrator/lib/dynafs.py
hydrator/lib/nextcloud.py
hydrator-0.2.0.dist-info/METADATA
hydrator-0.2.0.dist-info/WHEEL
hydrator-0.2.0.dist-info/entry_points.txt
hydrator-0.2.0.dist-info/top_level.txt
hydrator-0.2.0.dist-info/RECORD
