Metadata-Version: 2.1
Name: hydrator
Version: 0.2.0
Summary: Hydrate your development environment.
Home-page: https://git.niklasrosenstein.com/NiklasRosenstein/hydrator
Author: Niklas Rosenstein
Author-email: rosensteinniklas@gmail.com
License: MIT
Platform: UNKNOWN
Requires-Dist: click (<8.0.0,>=7.1.1)
Requires-Dist: nr.config (<0.2.0,>=0.1.0)
Requires-Dist: nr.databind.core (<0.1.0,>=0.0.8)
Requires-Dist: nr.databind.json (<0.1.0,>=0.0.7)
Requires-Dist: nr.fs (<2.0.0,>=1.6.0)
Requires-Dist: nr.proxy (<0.1.0,>=0.0.2)
Requires-Dist: PyYAML (<5.4.0,>=5.3.0)
Requires-Dist: requests (<3.0.0,>=2.23.0)
Requires-Dist: termcolor (<2.0.0,>=1.1.0)
